{"foods": [{"name": "Almond", "unit": "almond", "quantity": "1", "calories": "7.71"}, {"name": "Almond cake", "unit": "slice", "quantity": "1", "calories": "353.16"}, {"name": "Apple", "unit": "apple", "quantity": "1", "calories": "94.64"}, {"name": "Apple pie", "unit": "slice", "quantity": "1", "calories": "296.25"}, {"name": "Bacon", "unit": "slice", "quantity": "3", "calories": "161.46"}, {"name": "Bagel", "unit": "bagel", "quantity": "1", "calories": "277.2"}, {"name": "Banana", "unit": "banana", "quantity": "1", "calories": "105.02"}, {"name": "Beer", "unit": "bottle", "quantity": "1", "calories": "153.08"}, {"name": "Biscuits", "unit": "biscuit", "quantity": "1", "calories": "211.8"}, {"name": "Blueberry", "unit": "berry", "quantity": "1", "calories": "0.78"}, {"name": "Bread", "unit": "slice", "quantity": "1", "calories": "77.14"}, {"name": "Broccoli", "unit": "spear", "quantity": "1", "calories": "12.95"}, {"name": "Burrito", "unit": "burrito", "quantity": "1", "calories": "433.8"}, {"name": "Caesar salad", "unit": "bowl", "quantity": "1", "calories": "481.43"}, {"name": "Carrot", "unit": "unit", "quantity": "1", "calories": "16.1"}, {"name": "Carrot cake", "unit": "slice", "quantity": "1", "calories": "577.47"}, {"name": "Cheese", "unit": "slice", "quantity": "1", "calories": "113.12"}, {"name": "Cheesecake", "unit": "slice", "quantity": "1", "calories": "401.25"}, {"name": "Chicken wings", "unit": "wing", "quantity": "1", "calories": "87.74"}, {"name": "Chocolate", "unit": "piece", "quantity": "1", "calories": "37.45"}, {"name": "Chocolate cake", "unit": "slice", "quantity": "1", "calories": "424.01"}, {"name": "Chocolate mousse", "unit": "cup", "quantity": "0.5", "calories": "454.5"}, {"name": "Churros", "unit": "churro", "quantity": "1", "calories": "103.04"}, {"name": "Club sandwich", "unit": "sandwich", "quantity": "1", "calories": "816.84"}, {"name": "Coca cola", "unit": "can", "quantity": "1", "calories": "140"}, {"name": "Coconut", "unit": "cup", "quantity": "1", "calories": "387.6"}, {"name": "Coconut cake", "unit": "slice", "quantity": "1", "calories": "398.72"}, {"name": "Coffe", "unit": "cup", "quantity": "1", "calories": "2.37"}, {"name": "Coffee", "unit": "cup", "quantity": "1", "calories": "2.37"}, {"name": "Crepes", "unit": "crepe", "quantity": "1", "calories": "105.8"}, {"name": "Croissant", "unit": "croissant", "quantity": "1", "calories": "272.02"}, {"name": "Cupcake", "unit": "cupcake", "quantity": "1", "calories": "291.75"}, {"name": "Donut", "unit": "donut", "quantity": "1", "calories": "252.6"}, {"name": "Egg", "unit": "egg", "quantity": "1", "calories": "71.5"}, {"name": "French fries", "unit": "serving", "quantity": "1", "calories": "365.04"}, {"name": "Gelatin", "unit": "spoon", "quantity": "1", "calories": "23.45"}, {"name": "Grape", "unit": "grape", "quantity": "1", "calories": "33.81"}, {"name": "Grilled cheese sandwich", "unit": "piece", "quantity": "1", "calories": "365.76"}, {"name": "Hamburguer", "unit": "sandwich", "quantity": "1", "calories": "540.14"}, {"name": "Honey", "unit": "spoon", "quantity": "1", "calories": "63.84"}, {"name": "Hot dog", "unit": "unit", "quantity": "1", "calories": "154.56"}, {"name": "Ice cream", "unit": "cup", "quantity": "1", "calories": "273.24"}, {"name": "Iced tea", "unit": "cup", "quantity": "1", "calories": "2.37"}, {"name": "Iced tead", "unit": "cup", "quantity": "1", "calories": "2.37"}, {"name": "Lasagna", "unit": "serving", "quantity": "1", "calories": "602.49"}, {"name": "Lemonade", "unit": "cup", "quantity": "1", "calories": "98.8"}, {"name": "Lettuce", "unit": "cup", "quantity": "2", "calories": "15.98"}, {"name": "Lollipop", "unit": "unit", "quantity": "1", "calories": "23.64"}, {"name": "Macarons", "unit": "unit", "quantity": "1", "calories": "43.38"}, {"name": "Marshmallow", "unit": "unit", "quantity": "1", "calories": "22.9"}, {"name": "Meatballs", "unit": "unit", "quantity": "4", "calories": "324.32"}, {"name": "Melon", "unit": "slice", "quantity": "1", "calories": "60.18"}, {"name": "Milk", "unit": "cup", "quantity": "1", "calories": "124.95"}, {"name": "Milkshake", "unit": "cup", "quantity": "1", "calories": "454.4"}, {"name": "Muffin", "unit": "unit", "quantity": "1", "calories": "423.75"}, {"name": "Mushroom", "unit": "unit", "quantity": "1", "calories": "3.36"}, {"name": "Nachos", "unit": "order", "quantity": "1", "calories": "1233.77"}, {"name": "Olive", "unit": "olive", "quantity": "1", "calories": "4.37"}, {"name": "Omlete", "unit": "3-egg", "quantity": "1", "calories": "323.47"}, {"name": "Omelete", "unit": "3-egg", "quantity": "1", "calories": "323.47"}, {"name": "Onion", "unit": "piece", "quantity": "1", "calories": "41.36"}, {"name": "Orange", "unit": "piece", "quantity": "1", "calories": "68.6"}, {"name": "Oranje Juice", "unit": "cup", "quantity": "1", "calories": "111.6"}, {"name": "Orange juice", "unit": "cup", "quantity": "1", "calories": "111.6"}, {"name": "Pancakes", "unit": "unit", "quantity": "1", "calories": "90.8"}, {"name": "Pasta", "unit": "cup", "quantity": "1", "calories": "195.92"}, {"name": "Peanut", "unit": "unit", "quantity": "1", "calories": "5.87"}, {"name": "Peanut butter", "unit": "spoon", "quantity": "2", "calories": "188.16"}, {"name": "Pear", "unit": "unit", "quantity": "1", "calories": "101.46"}, {"name": "Pepperoni", "unit": "slice", "quantity": "1", "calories": "10.08"}, {"name": "Pickles", "unit": "spear", "quantity": "1", "calories": "4.2"}, {"name": "Pineapple", "unit": "cup", "quantity": "0.5", "calories": "41.25"}, {"name": "Pizza", "unit": "slice", "quantity": "1", "calories": "284.62"}, {"name": "Popcorn", "unit": "cup", "quantity": "1", "calories": "44"}, {"name": "Pretzel", "unit": "unit", "quantity": "1", "calories": "108.86"}, {"name": "Pudding", "unit": "cup", "quantity": "0.5", "calories": "143"}, {"name": "Raspberry", "unit": "berry", "quantity": "1", "calories": "1.04"}, {"name": "Rice", "unit": "cup", "quantity": "1", "calories": "205.4"}, {"name": "Shrimp", "unit": "unit", "quantity": "1", "calories": "5.95"}, {"name": "Spaghetti bolognese", "unit": "serving", "quantity": "1", "calories": "666.83"}, {"name": "Spaghetti carbonara", "unit": "plate", "quantity": "1", "calories": "1018.11"}, {"name": "Steak", "unit": "unit", "quantity": "1", "calories": "614.38"}, {"name": "Strawberry", "unit": "berry", "quantity": "5", "calories": "28.8"}, {"name": "Sushi", "unit": "roll", "quantity": "8", "calories": "348.54"}, {"name": "Tacos", "unit": "taco", "quantity": "1", "calories": "210.12"}, {"name": "Tea", "unit": "cup", "quantity": "1", "calories": "1.78"}, {"name": "Tomato", "unit": "unit", "quantity": "1", "calories": "22.14"}, {"name": "Waffle", "unit": "unit", "quantity": "1", "calories": "218.25"}, {"name": "Watermelon", "unit": "slice", "quantity": "1", "calories": "85.8"}, {"name": "Wine", "unit": "glass", "quantity": "1", "calories": "122.01"}]}